example.py
main.py
mcp_server.py
web_app.py
modules/__init__.py
modules/ai_analyzer.py
modules/data_fetcher.py
modules/technical_analyzer.py
modules/visualizer.py
iflow_mcp_ai_kline-0.1.2.dist-info/METADATA
iflow_mcp_ai_kline-0.1.2.dist-info/WHEEL
iflow_mcp_ai_kline-0.1.2.dist-info/entry_points.txt
iflow_mcp_ai_kline-0.1.2.dist-info/top_level.txt
iflow_mcp_ai_kline-0.1.2.dist-info/RECORD
