Metadata-Version: 2.4
Name: iflow-mcp_ai-kline
Version: 0.1.2
Summary: A股技术分析与AI预测工具
Requires-Python: >=3.12
Requires-Dist: python-dotenv
Requires-Dist: pandas
Requires-Dist: numpy
Requires-Dist: matplotlib
Requires-Dist: akshare
Requires-Dist: pandas-ta
Requires-Dist: scikit-learn
Requires-Dist: tables
Requires-Dist: pyarrow
Requires-Dist: mcp>=1.9.0
Requires-Dist: pyecharts
Requires-Dist: google-genai
Requires-Dist: openai>=1.0.0
